homes.py
homes-0.1.0.dist-info/METADATA
homes-0.1.0.dist-info/WHEEL
homes-0.1.0.dist-info/entry_points.txt
homes-0.1.0.dist-info/top_level.txt
homes-0.1.0.dist-info/RECORD
