Metadata-Version: 2.1
Name: homes
Version: 0.1.0
Summary: Add your description here
Requires-Python: >=3.11
Requires-Dist: click>=8.1.8
Requires-Dist: platformdirs>=4.3.6
Requires-Dist: promptic>=4.0.0
Requires-Dist: rich>=13.9.4
